{
  "$comment": "This file was autogenerated, DO NOT modify it by hand.",
  "$id": "extension-manifest.schema.json",
  "$schema": "http://json-schema.org/draft-07/schema#",
  "title": "Manifest for items of type extension",
  "type": "object",
  "properties": {
    "annotations": {
      "description": "Set of non-identifying key/value pairs akin to Kubernetes object annotations",
      "type": "object",
      "patternProperties": {
        "^([a-zA-Z0-9][a-zA-Z0-9\\.\\-]{0,253}[\\/])?([a-zA-Z0-9][a-zA-Z0-9\\.\\-]{0,63}[a-zA-Z0-9]?)$": {
          "type": "string",
          "pattern": "^$|^[a-zA-Z0-9](?:[a-zA-Z0-9._-]{0,61}[a-zA-Z0-9])?$",
          "maxLength": 63
        }
      },
      "additionalProperties": false
    },
    "categoryId": {
      "enum": [
        "stream",
        "business",
        "frontendbuilder",
        "monitoring",
        "utility",
        "auth",
        "database",
        "devportal",
        "files",
        "microfrontend",
        "notification",
        "orchestrators",
        "serverless",
        "code",
        "dotnetcore",
        "golang",
        "kotlin",
        "nodejs",
        "python",
        "rust",
        "spa",
        "insurance",
        "addgeo",
        "addonsecurity",
        "payments",
        "fast-data",
        "communication",
        "scheduling",
        "fast-data-connectors",
        "idm",
        "scoring",
        "data-catalog",
        "artificial-intelligence",
        "healthcare",
        "integrations"
      ],
      "type": "string"
    },
    "description": {
      "description": "Brief description of the item",
      "type": "string"
    },
    "documentation": {
      "description": "Documentation of the item",
      "properties": {
        "type": {
          "enum": [
            "externalLink",
            "markdown"
          ],
          "type": "string"
        },
        "url": {
          "type": "string"
        }
      },
      "required": [
        "type",
        "url"
      ],
      "type": "object"
    },
    "itemId": {
      "description": "RFC-1035 compliant identifier of the item. It forms a composite PK with tenantId and, if present, version.name",
      "type": "string",
      "pattern": "^[a-zA-Z0-9](?:[a-zA-Z0-9-]{0,61}[a-zA-Z0-9])?$",
      "minLength": 1,
      "maxLength": 63
    },
    "itemTypeDefinitionRef": {
      "additionalProperties": false,
      "properties": {
        "name": {
          "const": "extension"
        },
        "namespace": {
          "const": "mia-platform"
        }
      },
      "required": [
        "name",
        "namespace"
      ],
      "type": "object"
    },
    "labels": {
      "description": "Set of identifying key/value pairs akin to Kubernetes object labels",
      "type": "object",
      "patternProperties": {
        "^([a-zA-Z0-9][a-zA-Z0-9\\.\\-]{0,253}[\\/])?([a-zA-Z0-9][a-zA-Z0-9\\.\\-]{0,63}[a-zA-Z0-9]?)$": {
          "type": "string",
          "pattern": "^$|^[a-zA-Z0-9](?:[a-zA-Z0-9._-]{0,61}[a-zA-Z0-9])?$",
          "maxLength": 63
        }
      },
      "additionalProperties": false
    },
    "lifecycleStatus": {
      "description": "Lifecycle status of the item",
      "enum": [
        "coming-soon",
        "draft",
        "published",
        "maintenance",
        "deprecated",
        "archived"
      ],
      "type": "string"
    },
    "links": {
      "description": "List of external hyperlinks",
      "type": "array",
      "items": {
        "type": "object",
        "properties": {
          "url": {
            "description": "URL in standard uri format",
            "type": "string"
          },
          "displayName": {
            "description": "User friendly display name for the link",
            "type": "string"
          }
        },
        "additionalProperties": false,
        "required": [
          "url"
        ]
      }
    },
    "maintainers": {
      "description": "List of organizational entities maintaining the resource",
      "type": "array",
      "items": {
        "type": "object",
        "properties": {
          "name": {
            "description": "Display name of the entity",
            "type": "string",
            "minLength": 1
          },
          "email": {
            "description": "Contact email of the entity",
            "type": "string",
            "format": "email",
            "minLength": 1
          }
        },
        "additionalProperties": false,
        "required": [
          "name"
        ]
      }
    },
    "name": {
      "description": "Human-readable name of the item",
      "minLength": 1,
      "type": "string"
    },
    "providerId": {
      "description": "Identifier of the provider used to retrieve markdown documentation content and external resources, if supported by the item type",
      "type": "string"
    },
    "relationships": {
      "description": "List of relationships from the current Catalog entity to any other entity (either it part of the Catalog or not)",
      "type": "array",
      "items": {
        "type": "object",
        "properties": {
          "target": {
            "description": "The receiving end of the relationships. It can be a URN-reference to another Catalog entity or an arbitrary string",
            "type": "string"
          },
          "type": {
            "description": "The type of the relationships. It can be one of the Catalog well-known relationships or an arbitrary string",
            "type": "string"
          }
        },
        "additionalProperties": false,
        "required": [
          "target",
          "type"
        ]
      }
    },
    "releaseDate": {
      "description": "Creation date of this item's release",
      "format": "date-time",
      "type": "string"
    },
    "repositoryUrl": {
      "description": "URL of the repository containing the source code of the resource created by the item",
      "type": "string"
    },
    "resources": {
      "allOf": [
        {
          "if": {
            "properties": {
              "extensionType": {
                "enum": [
                  "iframe",
                  "external-link"
                ],
                "type": "string"
              }
            }
          },
          "then": {
            "properties": {
              "entry": {
                "type": "string"
              },
              "routes": {
                "items": {
                  "properties": {
                    "destinationPath": {
                      "type": "string"
                    },
                    "icon": {
                      "properties": {
                        "name": {
                          "type": "string"
                        }
                      },
                      "type": "object"
                    },
                    "id": {
                      "type": "string"
                    },
                    "labelIntl": {
                      "properties": {
                        "en": {
                          "type": "string"
                        },
                        "it": {
                          "type": "string"
                        }
                      },
                      "type": "object"
                    },
                    "locationId": {
                      "type": "string"
                    },
                    "matchExactMountPath": {
                      "type": "boolean"
                    },
                    "order": {
                      "type": "number"
                    },
                    "parentId": {
                      "type": "string"
                    },
                    "renderType": {
                      "enum": [
                        "category"
                      ],
                      "type": "string"
                    }
                  },
                  "required": [
                    "id",
                    "locationId",
                    "labelIntl"
                  ],
                  "type": "object"
                },
                "type": "array"
              }
            },
            "required": [
              "entry"
            ]
          }
        },
        {
          "if": {
            "properties": {
              "extensionType": {
                "const": "composer-page"
              }
            }
          },
          "then": {
            "properties": {
              "configuration": {
                "type": "string"
              }
            },
            "required": [
              "configuration"
            ]
          }
        }
      ],
      "description": "Assets used by Mia-Platform Console to create the item",
      "properties": {
        "contexts": {
          "items": {
            "enum": [
              "console",
              "project",
              "company"
            ],
            "type": "string"
          },
          "type": "array"
        },
        "extensionType": {
          "enum": [
            "iframe",
            "external-link",
            "composer-page"
          ],
          "type": "string"
        },
        "name": {
          "type": "string"
        },
        "permissions": {
          "items": {
            "type": "string"
          },
          "type": "array"
        },
        "roleIds": {
          "items": {
            "type": "string"
          },
          "type": "array"
        }
      },
      "required": [
        "name",
        "extensionType",
        "contexts"
      ],
      "type": "object",
      "examples": [
        {
          "name": "E-Commerce configurator",
          "extensionType": "iframe",
          "contexts": [
            "company"
          ],
          "entry": "https://e-commerce-configurator.com"
        },
        {
          "name": "E-Commerce dashboard",
          "extensionType": "external-link",
          "contexts": [
            "company"
          ],
          "entry": "https://e-commerce-dashboard.com"
        },
        {
          "name": "E-Commerce CMS",
          "extensionType": "composer-page",
          "contexts": [
            "project"
          ],
          "configuration": "{\"tag\":\"p\",\"content\":\"Hello!\"}"
        }
      ]
    },
    "supportedBy": {
      "enum": [
        "Mia-Platform",
        "Mia-FinTech",
        "Mia-Care",
        "Community"
      ],
      "type": "string"
    },
    "tags": {
      "description": "List of single-valued strings",
      "type": "array",
      "items": {
        "type": "string",
        "pattern": "^[a-z0-9:+#]+(-[a-z0-9:+#]+)*$",
        "minLength": 1,
        "maxLength": 63
      }
    },
    "tenantId": {
      "const": "mia-platform"
    },
    "visibility": {
      "additionalProperties": false,
      "properties": {
        "public": {
          "const": true
        }
      },
      "required": [
        "public"
      ],
      "type": "object"
    },
    "$schema": {
      "type": "string"
    },
    "image": {
      "additionalProperties": false,
      "properties": {
        "localPath": {
          "type": "string"
        }
      },
      "required": [
        "localPath"
      ],
      "type": "object"
    },
    "supportedByImage": {
      "additionalProperties": false,
      "properties": {
        "localPath": {
          "type": "string"
        }
      },
      "required": [
        "localPath"
      ],
      "type": "object"
    }
  },
  "additionalProperties": false,
  "required": [
    "name",
    "itemId",
    "tenantId",
    "resources",
    "lifecycleStatus",
    "categoryId",
    "image",
    "supportedBy",
    "supportedByImage",
    "visibility",
    "releaseDate",
    "itemTypeDefinitionRef"
  ]
}
